smm2sim
