Metadata-Version: 2.1
Name: smm2sim
Version: 1.0.3
Summary: A tool for simulating the GSA Mario Maker 2 Endless Expert League
Home-page: https://github.com/dmparker0/smm2sim/
Author: Dan Parker
Author-email: dan.m.parker0@gmail.com
License: MIT
Download-URL: https://github.com/dmparker0/smm2sim/archive/v1.0.3.tar.gz
Keywords: Mario,SMM,SMM2,GSA,speedrun,simulation,statistics
Platform: UNKNOWN
